retrying.py
retrying-1.3.6.dist-info/licenses/AUTHORS.rst
retrying-1.3.6.dist-info/licenses/LICENSE
retrying-1.3.6.dist-info/licenses/NOTICE
retrying-1.3.6.dist-info/METADATA
retrying-1.3.6.dist-info/WHEEL
retrying-1.3.6.dist-info/top_level.txt
retrying-1.3.6.dist-info/RECORD
